char_featurizer/__init__.py
char_featurizer/version.py
char_featurizer/chaizi/__init__.py
char_featurizer/chaizi/parse.py
char_featurizer/featurizer/__init__.py
char_featurizer/featurizer/chaizi.py
char_featurizer/featurizer/four_corner.py
char_featurizer/featurizer/pinyin.py
char_featurizer/featurizer/pinyin_parts.py
char_featurizer/four_corner/__init__.py
char_featurizer/four_corner/parse.py
char_featurizer/resource/data_chaizi.pkl
char_featurizer/resource/data_four_corner.pkl
example/__init__.py
example/example_as_tensor.py
example/normal_example.py
char_featurizer-1.0.0.dist-info/METADATA
char_featurizer-1.0.0.dist-info/WHEEL
char_featurizer-1.0.0.dist-info/top_level.txt
char_featurizer-1.0.0.dist-info/RECORD
