Metadata-Version: 2.1
Name: char-featurizer
Version: 1.0.0
Summary: 中文字符特征提取工具，可以从中文汉字中提取出拼音、声调、拆分偏旁部首、四角编码，并且可以转化为tensor作为模型的输入。
Home-page: https://github.com/charlesXu86/char_featurizer
Author: xu
Author-email: charlesxu86@163.com
License: MIT
Platform: UNKNOWN
Classifier: License :: OSI Approved :: MIT License
Classifier: Programming Language :: Python :: 3.4
Classifier: Programming Language :: Python :: 3.5
Classifier: Programming Language :: Python :: 3.6
Classifier: Programming Language :: Python :: 3.7
Classifier: Programming Language :: Python :: 3.8
Classifier: Programming Language :: Python :: Implementation :: CPython
Classifier: Programming Language :: Python :: Implementation :: PyPy
